MANIFEST.in
README.md
setup.cfg
setup.py
voice_analyzer/__init__.py
voice_analyzer/analyzer.py
voice_analyzer.egg-info/PKG-INFO
voice_analyzer.egg-info/SOURCES.txt
voice_analyzer.egg-info/dependency_links.txt
voice_analyzer.egg-info/requires.txt
voice_analyzer.egg-info/top_level.txt
voice_analyzer/models/sex/model.h5