Metadata-Version: 2.1
Name: voice-analyzer
Version: 1.0.0
Summary: Human voice analyzer
Home-page: https://github.com/artysold/voice-analyzer
Author: Artem Soldatov
Author-email: arty.sold@gmail.com
License: UNKNOWN
Platform: UNKNOWN
